{
  "sections": {
    "ea8479d2-0c1d-4e21-8752-556731abf541": {
      "type": "banner-new-rotation",
      "blocks": {
        "template--15628744687716__ea8479d2-0c1d-4e21-8752-556731abf541-1678514253ebb87161-0": {
          "type": "heading",
          "settings": {
            "heading": "Grande S1-Access a Brand New Home in 15 Mins",
            "heading_size": "h2",
            "font_size": 48,
            "margin_top": 24,
            "margin_bottom": 24,
            "heading_color": "#fff",
            "font_weight": 400
          }
        },
        "template--15628744687716__ea8479d2-0c1d-4e21-8752-556731abf541-1678514253ebb87161-5": {
          "type": "rotation-banner-img",
          "settings": {
            "rotation-banner-img-item": "shopify:\/\/shop_images\/bbb85c74b1455590c86e62f0eb884070.jpg"
          }
        },
        "5d7e473b-943c-4e7b-bb50-994399697b94": {
          "type": "rotation-banner-img",
          "disabled": true,
          "settings": {
            "rotation-banner-img-item": "shopify:\/\/shop_images\/16_1.png"
          }
        },
        "79b21d14-4c0c-4375-8a53-3265202a5e3f": {
          "type": "rotation-banner-img",
          "disabled": true,
          "settings": {
            "rotation-banner-img-item": "shopify:\/\/shop_images\/s2.png"
          }
        },
        "b22513aa-a4db-49f8-95e3-5422d6a4ab92": {
          "type": "buttons",
          "settings": {
            "banner_button_label": "Discover Your Needs",
            "banner_button_link": "https:\/\/form.jotform.com\/PODX\/design-yours",
            "font_size": 32,
            "button_color": "#9ED835"
          }
        },
        "d88616b2-88fb-40b7-8afa-8450b3a66252": {
          "type": "text",
          "settings": {
            "text": "Whether you're a new homeowner, seeking to travel with the convenience of home, or simply wanting to downsize with the option of an additional residence in your backyard, the Grande S1 is an intelligent choice for you!",
            "font_size": 24,
            "margin_top": 24,
            "margin_bottom": 24,
            "heading_color": "#fff",
            "font_weight": 400
          }
        }
      },
      "block_order": [
        "template--15628744687716__ea8479d2-0c1d-4e21-8752-556731abf541-1678514253ebb87161-0",
        "template--15628744687716__ea8479d2-0c1d-4e21-8752-556731abf541-1678514253ebb87161-5",
        "5d7e473b-943c-4e7b-bb50-994399697b94",
        "79b21d14-4c0c-4375-8a53-3265202a5e3f",
        "b22513aa-a4db-49f8-95e3-5422d6a4ab92",
        "d88616b2-88fb-40b7-8afa-8450b3a66252"
      ],
      "settings": {
        "text_place": "right",
        "image_overlay_opacity": 0,
        "image_height": "medium",
        "adapt_height_first_image": false,
        "desktop_content_position": "center",
        "show_text_box": true,
        "desktop_content_alignment": "center",
        "color_scheme": "background-1",
        "mobile_content_alignment": "center",
        "stack_images_on_mobile": true,
        "show_text_below": true
      }
    },
    "de5500d3-8001-4a1c-b0a8-3b41fcb86213": {
      "type": "only-text-mullited",
      "blocks": {
        "template--15628744687716__de5500d3-8001-4a1c-b0a8-3b41fcb86213-167851966228481248-0": {
          "type": "only-card-mullited-item",
          "settings": {
            "heading_label": "Ingenious Spaces Design",
            "heading_size": 28,
            "head_weight": 400,
            "text_label": "Living area, kitchen, bedroom, and bathroom included",
            "text_weight": 400,
            "text_size": 22
          }
        },
        "cc3926e9-97c1-42ef-a6df-e884fbb7363f": {
          "type": "only-card-mullited-item",
          "settings": {
            "heading_label": "Free to Move",
            "heading_size": 24,
            "head_weight": 400,
            "text_label": "Towable with F250 or equivalent, and assemble on-site within 15 mins",
            "text_weight": 400,
            "text_size": 20
          }
        },
        "0ea5ed2e-2389-4668-b635-464d2888acf8": {
          "type": "only-card-mullited-item",
          "settings": {
            "heading_label": "Reliability and Safety",
            "heading_size": 24,
            "head_weight": 400,
            "text_label": "The main structure is made of high-tensile steel filled with rigid polyurethan",
            "text_weight": 400,
            "text_size": 18
          }
        },
        "77e67c3e-fc08-4607-9128-e09dc81dc4eb": {
          "type": "only-card-mullited-item",
          "settings": {
            "heading_label": "Off-grid Solar Supported",
            "heading_size": 24,
            "head_weight": 400,
            "text_label": "Solar solutions powered by Renogy",
            "text_weight": 400,
            "text_size": 20
          }
        },
        "fd29c194-40b3-449d-a77e-1d66e82d8cdf": {
          "type": "only-card-mullited-item",
          "disabled": true,
          "settings": {
            "heading_label": "Smart Home Automation",
            "heading_size": 24,
            "head_weight": 400,
            "text_label": "EDGE ONE smart home security system is optional",
            "text_weight": 400,
            "text_size": 20
          }
        }
      },
      "block_order": [
        "template--15628744687716__de5500d3-8001-4a1c-b0a8-3b41fcb86213-167851966228481248-0",
        "cc3926e9-97c1-42ef-a6df-e884fbb7363f",
        "0ea5ed2e-2389-4668-b635-464d2888acf8",
        "77e67c3e-fc08-4607-9128-e09dc81dc4eb",
        "fd29c194-40b3-449d-a77e-1d66e82d8cdf"
      ],
      "settings": {
        "padding_top": 40,
        "padding_bottom": 52
      }
    },
    "8266b8e9-d848-4c2c-8fcc-235bacf4683a": {
      "type": "welcome_width-video",
      "blocks": {
        "template--15628744687716__8266b8e9-d848-4c2c-8fcc-235bacf4683a-1678542519e08fca2e-0": {
          "type": "heading",
          "settings": {
            "heading": "WELCOME !",
            "heading_size": "h1",
            "font_size": 68,
            "margin_top": 124,
            "margin_bottom": 24,
            "heading_color": "#000",
            "font_weight": 400
          }
        },
        "template--15628744687716__8266b8e9-d848-4c2c-8fcc-235bacf4683a-1678542519e08fca2e-1": {
          "type": "button",
          "settings": {
            "button_label_1": "Customize Your Home",
            "button_link_1": "https:\/\/podxgo.com\/products\/order-now",
            "button_style_secondary_1": false,
            "button_color": "#000",
            "margin_top": 0,
            "margin_bottom": 0
          }
        }
      },
      "block_order": [
        "template--15628744687716__8266b8e9-d848-4c2c-8fcc-235bacf4683a-1678542519e08fca2e-0",
        "template--15628744687716__8266b8e9-d848-4c2c-8fcc-235bacf4683a-1678542519e08fca2e-1"
      ],
      "settings": {
        "heading": "Video",
        "heading_size": "h1",
        "cover_image": "shopify:\/\/shop_images\/7.png",
        "video_url": "",
        "button_label": "player",
        "padding_top": 36,
        "padding_bottom": 36,
        "font_size": 20,
        "font_weight": 400
      }
    },
    "adcf793c-7215-47db-b4c5-2a1a116c2315": {
      "type": "card-component-with-placediy",
      "blocks": {
        "template--15628744687716__adcf793c-7215-47db-b4c5-2a1a116c2315-16786750899a6fa3f1-0": {
          "type": "with_bg_card_placediy",
          "settings": {
            "picture-card-item": "shopify:\/\/shop_images\/1_dffdb5e9-cabb-4fa5-94b4-3537a77757ed.png",
            "heading": "Compact Tailer",
            "font_size": 42,
            "font_color": "#fff",
            "wrapper_place": "left-bottom",
            "heading_1": "125 sq.ft Relax Space",
            "heading_2": "18,000-19,000 lbs",
            "heading_3": "Travel Trailer With NOAH Seal",
            "text_font_size": 20,
            "text_font_weight": 400,
            "bg_opcity": 0,
            "button_label_1": "",
            "button_link_1": ""
          }
        },
        "d22b28e9-0cb0-4385-9032-e7da08a1d85a": {
          "type": "with_bg_card_placediy",
          "settings": {
            "picture-card-item": "shopify:\/\/shop_images\/free_to_move_tiny_house.png",
            "heading": "Free to Move",
            "font_size": 42,
            "font_color": "#fff",
            "wrapper_place": "left-bottom",
            "heading_1": "Towable with F250 or equivalent",
            "heading_2": "Easier titling and registration",
            "heading_3": "with proper certification",
            "text_font_size": 20,
            "text_font_weight": 400,
            "bg_opcity": 0,
            "button_label_1": "",
            "button_link_1": ""
          }
        },
        "66e4201c-8775-4442-ba3e-ab1d7ab4e474": {
          "type": "with_bg_card_placediy",
          "settings": {
            "picture-card-item": "shopify:\/\/shop_images\/22_59fad4d5-e064-4e5c-a319-ce725156bf22.png",
            "heading": "364 ft² Home",
            "font_size": 42,
            "font_color": "#fff",
            "wrapper_place": "left-bottom",
            "heading_1": "19'2.9'' L x 23'0.7'' W x 11'5.8'' H ",
            "heading_2": "Simple push of a button to easy setup and takedown, and automatic leveling",
            "heading_3": "",
            "text_font_size": 20,
            "text_font_weight": 400,
            "bg_opcity": 0,
            "button_label_1": "",
            "button_link_1": ""
          }
        }
      },
      "block_order": [
        "template--15628744687716__adcf793c-7215-47db-b4c5-2a1a116c2315-16786750899a6fa3f1-0",
        "d22b28e9-0cb0-4385-9032-e7da08a1d85a",
        "66e4201c-8775-4442-ba3e-ab1d7ab4e474"
      ],
      "settings": {
        "color_scheme": "background-1"
      }
    },
    "df8833a6-0d6a-4ac4-81dc-0271cbeb1884": {
      "type": "lr-block-with-rotation",
      "blocks": {
        "template--15628744687716__df8833a6-0d6a-4ac4-81dc-0271cbeb1884-167867630444b0c556-0": {
          "type": "heading",
          "settings": {
            "heading": "Proven Durability & Healthy",
            "heading_size": "h1",
            "is_show": "false",
            "font-weight": 600,
            "font_size": 50,
            "margin-top": 0,
            "margin-bottom": 0,
            "font_color": "#000"
          }
        },
        "template--15628744687716__df8833a6-0d6a-4ac4-81dc-0271cbeb1884-167867630444b0c556-1": {
          "type": "text",
          "settings": {
            "text": "A sealed folding dwelling built with the PODX GO® Hyadraulic System and solid steel structure that can be put in a variety of environments. All parts are manufactured in a highly precise factory and carefully packaged just for you.",
            "text_style": "body",
            "font_size": 24,
            "font_weight": 400,
            "margin-top": 16,
            "margin-bottom": 34,
            "font_color": "#000"
          }
        },
        "template--15628744687716__df8833a6-0d6a-4ac4-81dc-0271cbeb1884-167867630444b0c556-5": {
          "type": "right_text_wrapper",
          "settings": {
            "right_text": "",
            "font_size": 24,
            "is_border": "false"
          }
        },
        "a2bc290a-f290-43f3-af21-6fb3375bc4e8": {
          "type": "image_wrapper",
          "settings": {
            "image_1": "shopify:\/\/shop_images\/tiny_house_design_6dde8f30-5553-4945-9665-19f9becd3f93.png"
          }
        },
        "fafbf185-29d6-4eb4-bafc-f16d5c55e830": {
          "type": "pictureCard",
          "settings": {
            "picture-card-item": "shopify:\/\/shop_images\/31.png",
            "image_width": 110
          }
        },
        "439ce4d6-e51a-4544-84f1-a46504409821": {
          "type": "pictureCard",
          "settings": {
            "picture-card-item": "shopify:\/\/shop_images\/42.png",
            "image_width": 90
          }
        },
        "9224c4e8-f3b1-4797-88ca-ed41f3e8dfd3": {
          "type": "pictureCard",
          "settings": {
            "picture-card-item": "shopify:\/\/shop_images\/53.png",
            "image_width": 98
          }
        },
        "b6df34be-bc07-411b-b22a-9a0f74e2838a": {
          "type": "img_rotation",
          "settings": {
            "img_rotation": "shopify:\/\/shop_images\/2_313090bd-adf4-4f12-b97f-63b9ae75b0b1.jpg"
          }
        },
        "7a8790ab-3c82-4fc0-9f58-f24c65f2bdea": {
          "type": "img_rotation",
          "settings": {
            "img_rotation": "shopify:\/\/shop_images\/33333.jpg"
          }
        },
        "75d17d0e-ec57-4b45-b7e4-3a04440abf4e": {
          "type": "img_rotation",
          "settings": {
            "img_rotation": "shopify:\/\/shop_images\/1111.png"
          }
        }
      },
      "block_order": [
        "template--15628744687716__df8833a6-0d6a-4ac4-81dc-0271cbeb1884-167867630444b0c556-0",
        "template--15628744687716__df8833a6-0d6a-4ac4-81dc-0271cbeb1884-167867630444b0c556-1",
        "template--15628744687716__df8833a6-0d6a-4ac4-81dc-0271cbeb1884-167867630444b0c556-5",
        "a2bc290a-f290-43f3-af21-6fb3375bc4e8",
        "fafbf185-29d6-4eb4-bafc-f16d5c55e830",
        "439ce4d6-e51a-4544-84f1-a46504409821",
        "9224c4e8-f3b1-4797-88ca-ed41f3e8dfd3",
        "b6df34be-bc07-411b-b22a-9a0f74e2838a",
        "7a8790ab-3c82-4fc0-9f58-f24c65f2bdea",
        "75d17d0e-ec57-4b45-b7e4-3a04440abf4e"
      ],
      "settings": {
        "is_lr": "true",
        "margin_top": 24,
        "margin_bottom": 24,
        "show_text_box": true,
        "rotation_class": "swiper1",
        "layout": "text_first",
        "is_imgBg": "true"
      }
    },
    "29ac9adf-b455-4c37-8929-631cd309bf80": {
      "type": "lr-block-with-rotation",
      "blocks": {
        "template--15628744687716__29ac9adf-b455-4c37-8929-631cd309bf80-167876074482a92fd6-0": {
          "type": "heading",
          "settings": {
            "heading": "EDGE ONE",
            "heading_size": "h1",
            "is_show": "true",
            "font-weight": 400,
            "font_size": 50,
            "margin-top": 0,
            "margin-bottom": 16,
            "font_color": "#000"
          }
        },
        "dc238b2a-62c1-4f7d-82fc-12e9d70739a4": {
          "type": "heading",
          "settings": {
            "heading": "Your Smart Housekeeper",
            "heading_size": "h1",
            "is_show": "false",
            "font-weight": 400,
            "font_size": 50,
            "margin-top": 0,
            "margin-bottom": 44,
            "font_color": "#000"
          }
        },
        "template--15628744687716__29ac9adf-b455-4c37-8929-631cd309bf80-167876074482a92fd6-1": {
          "type": "text",
          "settings": {
            "text": "Your PODX GO is not just a house with pre-equipped furniture. It is connected with your feelings and activities.",
            "text_style": "body",
            "font_size": 24,
            "font_weight": 400,
            "margin-top": 0,
            "margin-bottom": 0,
            "font_color": "#000"
          }
        },
        "template--15628744687716__29ac9adf-b455-4c37-8929-631cd309bf80-167876074482a92fd6-5": {
          "type": "right_text_wrapper",
          "settings": {
            "right_text": "",
            "font_size": 24,
            "is_border": "false"
          }
        },
        "template--15628744687716__29ac9adf-b455-4c37-8929-631cd309bf80-167876074482a92fd6-6": {
          "type": "img_rotation",
          "settings": {
            "img_rotation": "shopify:\/\/shop_images\/edge_one_tiny_house_control.png"
          }
        },
        "9793f59f-382f-4a82-a4b4-a5974590f3ae": {
          "type": "img_rotation",
          "settings": {
            "img_rotation": "shopify:\/\/shop_images\/1_4f318e4e-35f3-4629-b1a6-8a0126a3866f.png"
          }
        },
        "438c5f72-eba4-4c8d-bbc4-06b728e9fd10": {
          "type": "img_rotation",
          "settings": {
            "img_rotation": "shopify:\/\/shop_images\/2_3e7d64c8-a27e-4a84-aa45-dd541d9f4954.png"
          }
        },
        "2eebd45e-42a6-48d7-93a5-d1423fc07252": {
          "type": "img_rotation",
          "settings": {
            "img_rotation": "shopify:\/\/shop_images\/3_daae3879-1b19-411b-bd98-6de73e1a61ad.png"
          }
        },
        "e1ae0dfc-0b3e-475e-9fb1-c1bcfbeae43b": {
          "type": "text",
          "settings": {
            "text": "Thanks to Edge ONE, the all-in-one solution for home automation, security system, and energy management, now everything will be under your control with only ONE command touchpad!",
            "text_style": "body",
            "font_size": 24,
            "font_weight": 400,
            "margin-top": 52,
            "margin-bottom": 0,
            "font_color": "#000"
          }
        }
      },
      "block_order": [
        "template--15628744687716__29ac9adf-b455-4c37-8929-631cd309bf80-167876074482a92fd6-0",
        "dc238b2a-62c1-4f7d-82fc-12e9d70739a4",
        "template--15628744687716__29ac9adf-b455-4c37-8929-631cd309bf80-167876074482a92fd6-1",
        "template--15628744687716__29ac9adf-b455-4c37-8929-631cd309bf80-167876074482a92fd6-5",
        "template--15628744687716__29ac9adf-b455-4c37-8929-631cd309bf80-167876074482a92fd6-6",
        "9793f59f-382f-4a82-a4b4-a5974590f3ae",
        "438c5f72-eba4-4c8d-bbc4-06b728e9fd10",
        "2eebd45e-42a6-48d7-93a5-d1423fc07252",
        "e1ae0dfc-0b3e-475e-9fb1-c1bcfbeae43b"
      ],
      "disabled": true,
      "settings": {
        "is_lr": "true",
        "margin_top": 24,
        "margin_bottom": 24,
        "show_text_box": true,
        "rotation_class": "swiper2",
        "layout": "image_first",
        "is_imgBg": "false"
      }
    },
    "e0d831ae-dfb5-4164-af60-f1358bf25b9a": {
      "type": "lr-block-with-rotation",
      "blocks": {
        "template--15628744687716__e0d831ae-dfb5-4164-af60-f1358bf25b9a-167876074482a92fd6-0": {
          "type": "heading",
          "settings": {
            "heading": "Sustainability& Energy Freedom",
            "heading_size": "h1",
            "is_show": "false",
            "font-weight": 400,
            "font_size": 50,
            "margin-top": 0,
            "margin-bottom": 0,
            "font_color": "#000"
          }
        },
        "template--15628744687716__e0d831ae-dfb5-4164-af60-f1358bf25b9a-167876074482a92fd6-1": {
          "type": "text",
          "settings": {
            "text": "Having a solar system allows you to live away from the electricity grid.  But in addition, it can also help you reduce your electricity bills, and it's also a reliable emergency backup power source. PODX GO homes offer you an Energy Freedom Package with  Renogy Lycan 5000 Power Box, the all-in-one solar and energy storage solutions that start from 5kWh to 40kWh.",
            "text_style": "body",
            "font_size": 24,
            "font_weight": 400,
            "margin-top": 44,
            "margin-bottom": 0,
            "font_color": "#000"
          }
        },
        "template--15628744687716__e0d831ae-dfb5-4164-af60-f1358bf25b9a-167876074482a92fd6-6": {
          "type": "img_rotation",
          "settings": {
            "img_rotation": "shopify:\/\/shop_images\/rng_1.png"
          }
        },
        "ac8df8ae-957e-46b1-aab1-1947320529f1": {
          "type": "img_rotation",
          "settings": {
            "img_rotation": "shopify:\/\/shop_images\/trailer_1.png"
          }
        },
        "d5f2e08a-cfb3-453d-a8d5-b93d6cb05e52": {
          "type": "img_rotation",
          "disabled": true,
          "settings": {
            "img_rotation": "shopify:\/\/shop_images\/lQDPJxbcK-1QfAnNCxLNE4iwyAD-Uopcgm4DacuYQUCFAA_5000_2834_b6f78537-71d2-4687-be05-da08d33906e5.jpg"
          }
        }
      },
      "block_order": [
        "template--15628744687716__e0d831ae-dfb5-4164-af60-f1358bf25b9a-167876074482a92fd6-0",
        "template--15628744687716__e0d831ae-dfb5-4164-af60-f1358bf25b9a-167876074482a92fd6-1",
        "template--15628744687716__e0d831ae-dfb5-4164-af60-f1358bf25b9a-167876074482a92fd6-6",
        "ac8df8ae-957e-46b1-aab1-1947320529f1",
        "d5f2e08a-cfb3-453d-a8d5-b93d6cb05e52"
      ],
      "settings": {
        "is_lr": "true",
        "margin_top": 24,
        "margin_bottom": 24,
        "show_text_box": true,
        "rotation_class": "swiper3",
        "layout": "text_first",
        "is_imgBg": "false"
      }
    },
    "018d58da-5bb3-4681-b2f0-cdbb5ee74504": {
      "type": "rich-text-bottom-img",
      "blocks": {
        "template--15634989645924__018d58da-5bb3-4681-b2f0-cdbb5ee74504-1684481610b45dbddd-0": {
          "type": "heading",
          "settings": {
            "heading": "<p>Need Financing?<\/p>",
            "heading_size": "h1",
            "font-weight": 400,
            "font_size": 48,
            "heading_color": "#333333"
          }
        },
        "template--15634989645924__018d58da-5bb3-4681-b2f0-cdbb5ee74504-1684481610b45dbddd-1": {
          "type": "text",
          "settings": {
            "text": "<p>We've teamed up with Acorn to provide financing solutions for those in need of assistance purchasing a PODX GO home. Now, owning your dream home is more accessible than ever before. Don't miss out on this opportunity – let us help you make your tiny home dreams a reality!<\/p><p><\/p>",
            "font-weight": 400,
            "font_size": 18,
            "text_color": "#333333"
          }
        },
        "template--15634989645924__018d58da-5bb3-4681-b2f0-cdbb5ee74504-1684481610b45dbddd-2": {
          "type": "yellow_border",
          "settings": {
          }
        },
        "template--15634989645924__018d58da-5bb3-4681-b2f0-cdbb5ee74504-1684481610b45dbddd-3": {
          "type": "text-with-img",
          "settings": {
            "logo": "shopify:\/\/shop_images\/acorn-finance-banner-easy-payment-options-horizontal-medium_c1814190-2521-4b4a-99ff-b2add158dac3.png",
            "img_link": "https:\/\/www.acornfinance.com\/apply?d=ZJY2W#\/personal"
          }
        }
      },
      "block_order": [
        "template--15634989645924__018d58da-5bb3-4681-b2f0-cdbb5ee74504-1684481610b45dbddd-0",
        "template--15634989645924__018d58da-5bb3-4681-b2f0-cdbb5ee74504-1684481610b45dbddd-1",
        "template--15634989645924__018d58da-5bb3-4681-b2f0-cdbb5ee74504-1684481610b45dbddd-2",
        "template--15634989645924__018d58da-5bb3-4681-b2f0-cdbb5ee74504-1684481610b45dbddd-3"
      ],
      "settings": {
        "is_border": "true",
        "is_background_radius": "true",
        "padding_top": 40,
        "padding_bottom": 52
      }
    },
    "8e9745a6-c196-473d-b0bb-baed509eb47e": {
      "type": "rich-text-new",
      "blocks": {
        "template--15628744687716__8e9745a6-c196-473d-b0bb-baed509eb47e-1678762114c2d9a833-1": {
          "type": "text",
          "settings": {
            "text": "<p>Having questions about start your tiny home journey? <\/p>",
            "font-weight": 400,
            "font_size": 30,
            "text_color": "#000"
          }
        },
        "template--15628744687716__8e9745a6-c196-473d-b0bb-baed509eb47e-1678762114c2d9a833-0": {
          "type": "heading",
          "settings": {
            "heading": "<p>No worries. We are here to help. <\/p>",
            "heading_size": "h1",
            "font-weight": 400,
            "font_size": 46,
            "heading_color": "#000"
          }
        }
      },
      "block_order": [
        "template--15628744687716__8e9745a6-c196-473d-b0bb-baed509eb47e-1678762114c2d9a833-1",
        "template--15628744687716__8e9745a6-c196-473d-b0bb-baed509eb47e-1678762114c2d9a833-0"
      ],
      "settings": {
        "is_border": "false",
        "is_background_radius": "false",
        "padding_top": 86,
        "padding_bottom": 84
      }
    },
    "main": {
      "type": "main-page",
      "disabled": true,
      "settings": {
        "padding_top": 36,
        "padding_bottom": 36
      }
    },
    "4a6aed55-5b72-479d-aa4f-cf8629c1247a": {
      "type": "rich-text-image",
      "blocks": {
        "template--15559734788196__4a6aed55-5b72-479d-aa4f-cf8629c1247a-1671587908d557e879-0": {
          "type": "heading",
          "settings": {
            "heading": "<p><strong>You have more questions?<\/strong><\/p>",
            "heading_size": "h1",
            "font-weight": 400
          }
        },
        "template--15559734788196__4a6aed55-5b72-479d-aa4f-cf8629c1247a-1671587908d557e879-2": {
          "type": "text",
          "settings": {
            "text": "<p>Our 24\/7 customer service will reach out to you ASAP.<\/p>"
          }
        },
        "template--15559734788196__4a6aed55-5b72-479d-aa4f-cf8629c1247a-1671587908d557e879-3": {
          "type": "button",
          "settings": {
            "button_label": "CONTACT US",
            "button_link": "shopify:\/\/pages\/contact",
            "button_style_secondary": false,
            "button_background": "#B5EF35",
            "btn_radius": 0
          }
        }
      },
      "block_order": [
        "template--15559734788196__4a6aed55-5b72-479d-aa4f-cf8629c1247a-1671587908d557e879-0",
        "template--15559734788196__4a6aed55-5b72-479d-aa4f-cf8629c1247a-1671587908d557e879-2",
        "template--15559734788196__4a6aed55-5b72-479d-aa4f-cf8629c1247a-1671587908d557e879-3"
      ],
      "disabled": true,
      "settings": {
        "desktop_content_position": "center",
        "content_alignment": "center",
        "color_scheme": "accent-1",
        "full_width": true,
        "padding_top": 40,
        "padding_bottom": 52
      }
    },
    "6c65b232-5d4c-4c18-8dce-4ad47c38e8b1": {
      "type": "picture-card-with-bg",
      "blocks": {
        "template--15597986709604__6c65b232-5d4c-4c18-8dce-4ad47c38e8b1-16767018167eaff61e-3": {
          "type": "picture_card_big",
          "settings": {
            "picture_item": "shopify:\/\/shop_images\/3_1219730f-5c74-4768-9889-00becd5f19f3.jpg",
            "heading_1": "How will you get",
            "heading_2": "your PODX GO home?",
            "button_label_1": "Learn More",
            "button_link_1": "shopify:\/\/blogs\/how-to\/process-of-buying-podxgo"
          }
        },
        "template--15597986709604__6c65b232-5d4c-4c18-8dce-4ad47c38e8b1-16767018167eaff61e-4": {
          "type": "picture_card",
          "settings": {
            "picture_item": "shopify:\/\/shop_images\/deserted-farm-housing-in-baren-lands.jpg",
            "heading_1": "How to properly",
            "heading_2": "zone your tiny house?",
            "item_height": "400",
            "button_label_1": "Learn More",
            "button_link_1": "shopify:\/\/blogs\/zoning\/how-to-properly-zone-insure-your-tiny-house-in-the-us-a-step-by-step-guide"
          }
        },
        "7fe64ae1-f6ba-4465-ada8-2843b3183ae5": {
          "type": "picture_card",
          "settings": {
            "picture_item": "shopify:\/\/shop_images\/rooftops-and-pools-of-a-florida-residential-neighbourhood.jpg",
            "heading_1": "Become our partner",
            "heading_2": "in your neighborhood",
            "item_height": "266",
            "button_label_1": "Learn More",
            "button_link_1": "https:\/\/form.jotform.com\/PODX\/dealer-application"
          }
        }
      },
      "block_order": [
        "template--15597986709604__6c65b232-5d4c-4c18-8dce-4ad47c38e8b1-16767018167eaff61e-3",
        "template--15597986709604__6c65b232-5d4c-4c18-8dce-4ad47c38e8b1-16767018167eaff61e-4",
        "7fe64ae1-f6ba-4465-ada8-2843b3183ae5"
      ],
      "settings": {
        "is_titleBlock": "false",
        "href_url_id": "",
        "max_width": "",
        "is_showTitle": "true",
        "layout": "big_image_first",
        "padding_top": 24,
        "padding_bottom": 24
      }
    },
    "fa906ac5-c0c8-4c60-bb42-a7cc9ffb22d6": {
      "type": "newsletter",
      "blocks": {
        "template--15559734788196__fa906ac5-c0c8-4c60-bb42-a7cc9ffb22d6-16740930612d09df19-0": {
          "type": "heading",
          "settings": {
            "heading": "Sign Up and Stay Tuned",
            "heading_size": "h1"
          }
        },
        "template--15559734788196__fa906ac5-c0c8-4c60-bb42-a7cc9ffb22d6-16740930612d09df19-1": {
          "type": "paragraph",
          "settings": {
            "text": "<p>Tiny Home Tips and Stories \/ Sustainable Living Tips \/ New Models \/ Campaigns<\/p>"
          }
        },
        "template--15559734788196__fa906ac5-c0c8-4c60-bb42-a7cc9ffb22d6-16740930612d09df19-2": {
          "type": "email_form",
          "settings": {
          }
        }
      },
      "block_order": [
        "template--15559734788196__fa906ac5-c0c8-4c60-bb42-a7cc9ffb22d6-16740930612d09df19-0",
        "template--15559734788196__fa906ac5-c0c8-4c60-bb42-a7cc9ffb22d6-16740930612d09df19-1",
        "template--15559734788196__fa906ac5-c0c8-4c60-bb42-a7cc9ffb22d6-16740930612d09df19-2"
      ],
      "settings": {
        "href_id": "",
        "is_background_radius": "true",
        "color_scheme": "background-1",
        "full_width": true,
        "padding_top": 40,
        "padding_bottom": 52
      }
    }
  },
  "order": [
    "ea8479d2-0c1d-4e21-8752-556731abf541",
    "de5500d3-8001-4a1c-b0a8-3b41fcb86213",
    "8266b8e9-d848-4c2c-8fcc-235bacf4683a",
    "adcf793c-7215-47db-b4c5-2a1a116c2315",
    "df8833a6-0d6a-4ac4-81dc-0271cbeb1884",
    "29ac9adf-b455-4c37-8929-631cd309bf80",
    "e0d831ae-dfb5-4164-af60-f1358bf25b9a",
    "018d58da-5bb3-4681-b2f0-cdbb5ee74504",
    "8e9745a6-c196-473d-b0bb-baed509eb47e",
    "main",
    "4a6aed55-5b72-479d-aa4f-cf8629c1247a",
    "6c65b232-5d4c-4c18-8dce-4ad47c38e8b1",
    "fa906ac5-c0c8-4c60-bb42-a7cc9ffb22d6"
  ]
}
